Workbook

Sheet Dashboard Executivo
A1: ORIZON | Dashboard Executivo
A2: Carteira 2026 inicializada do zero: score ORIZON reformulado para priorizacao operacional
A4: Indicador | B4: Valor | D4: Nivel reformulado | E4: Clientes | F4: Score medio | G4: Credito recomendado | I4: Fila inicial | J4: Clientes | K4: Score medio | L4: Credito
A5: Clientes mapeados | B5: 45 | D5: FOUNDATION | E5: 17 | F5: 40.235294 | G5: 1840 | I5: Fila 1 - plano executivo imediato | J5: 14 | K5: 92.785714 | L5: 403312.5
A6: Area total ha | B6: 3956005 | D6: FLOW | E6: 5 | F6: 63.8 | G6: 28840 | I6: Fila 2 - conversao assistida 30 dias | J6: 9 | K6: 77.777778 | L6: 116133
A7: Score medio reformulado | B7: 66.711111 | D7: PRIME | E7: 9 | F7: 77.777778 | G7: 116133 | I7: Fila 3 - prova de valor 60 dias | J7: 5 | K7: 63.8 | L7: 28840
A8: Credito recomendado | B8: 550125.5 | D8: LEGACY | E8: 14 | F8: 92.785714 | G8: 403312.5 | I8: Fila 4 - qualificacao sem investimento | J8: 17 | K8: 40.235294 | L8: 1840
A9: Clientes PRIME+ | B9: 23 | D9: Total | E9: 45 | F9: 66.711111 | G9: 550125.5 | I9: Total filas | J9: 45 | K9: 66.711111 | L9: 550125.5
A10: Fila 1 imediata | B10: 14
A12: Raizen Piloto LEGACY | B12: Valor
A13: Cotacao cheia 30d | B13: 47410250
A14: Cotacao cheia 90d | B14: 50179433
A15: Volume cheio | B15: 463810
A16: Credito ponderado ref. | B16: 2979620
A17: TCH Ano 1 | B17: 174000
A18: Mais Maquinas Ano 2 | B18: 158500

Sheet Raizen Piloto LEGACY
A1: ORIZON | Raizen Piloto LEGACY
A2: Cliente ancora do projeto: piloto enterprise com governanca, validacao tecnica e evolucao plurianual
A4: Bloco | B4: Decisao | C4: Racional | D4: Como apresentar | E4: Gatilho | F4: Indicador
A5: Posicionamento | B5: Raizen como LEGACY PILOTO | C5: Porte, vitrine setorial e potencial de contrato de longo prazo | D5: Nao e campanha; e plataforma de evolucao operacional | E5: Aprovacao diretoria NOOA | F5: Patrocinio interno
A6: Cotacao | B6: Manter volume cheio | C6: Preco cheio ja enviado e deve preservar ambicao comercial | D6: Apresentar como potencial de escala, nao como obrigacao de entrada | E6: Alinhamento suprimentos/agricola | F6: Valor 30d/90d
A7: Entrada 2026 | B7: Piloto executivo | C7: AURAS positivo e AUBA aguardando resultado exigem etapa de validacao | D7: Areas semi-comerciais + governanca ORIZON | E7: Definir unidades-piloto | F7: Hectares validados
A8: Ano 1 | B8: TCH como braco tecnico | C8: Diagnostico e treinamento sustentam credibilidade e padronizacao | D8: Diagnosticar, corrigir, mensurar | E8: Agenda tecnica mensal | F8: Laudos e treinamentos
A9: Ano 2 | B9: Mais Maquinas como evolucao estrutural | C9: Depois da validacao, ativar mecanizacao e sistemas de aplicacao | D9: Coparticipacao ORIZON com teto e contrato | E9: Renovacao/expansao | F9: Projetos implantados
A10: Governanca | B10: Comite ORIZON Raizen | C10: Conta enterprise exige rotina executiva | D10: NOOA + Raizen + TCH + Mais Maquinas | E10: Reuniao mensal | F10: Plano de acao
A11: Politica | B11: Credito operacional por fase | C11: Evita rebate e protege margem | D11: Credito bruto vira budget elegivel, liberado por marcos | E11: Metas tecnicas cumpridas | F11: ROI operacional
A12: Saida esperada | B12: Case enterprise | C12: Primeiro cliente ancora do ORIZON | D12: Relatorio executivo de evolucao | E12: Resultados validados | F12: Contrato plurianual
A15: Orcamento tecnico do piloto | B15: Quantidade | C15: Valor unitario | D15: Valor total | E15: Ano | F15: Observacao
A16: Diagnostico TCH | B16: 60 | C16: 900 | D16: 54000 | E16: 2026 | F16: Diagnosticos por unidade/operacao critica
A17: Treinamento TCH | B17: 24 | C17: 5000 | D17: 120000 | E17: 2026 | F17: Treinamento de equipes e padronizacao
A18: Subtotal TCH Ano 1 | D18: 174000 | E18: 2026 | F18: Base minima para piloto LEGACY
A19: Carteira Mais Maquinas | D19: 317000 | E19: 2027 | F19: Projetos estruturais pos-validacao
A20: Participacao ORIZON Mais Maquinas | B20: 0.5 | D20: 158500 | E20: 2027 | F20: Liberacao condicionada a contrato e metas
A21: Credito ponderado ref. volume cheio | D21: 2979620 | E21: Referencia | F21: Nao liberar integralmente
A22: Saldo estrategico reservado | D22: 2647120 | E22: 2027+ | F22: Usar apenas com expansao validada

Sheet Cotacao Raizen Cheia
A1: ORIZON | Cotacao Raizen Cheia
A2: Volume cheio enviado como referencia comercial; usar como visao de escala, nao como entrada transacional
A4: Produto | B4: Area ha | C4: Dose | D4: Volume cheio | E4: Preco 30d | F4: Total 30d | G4: Preco 90d | H4: Total 90d | I4: Credito ponderado | J4: Papel ORIZON
A5: AUFIX | B5: 270000 | C5: 0.3 | D5: 81000 | E5: 22 | F5: 1782000 | G5: 24.21 | H5: 1961010 | I5: 324000 | J5: Estrutural B2B
A6: AURAS | B6: 270000 | C6: 0.25 | D6: 67500 | E6: 220.5 | F6: 14883750 | G6: 234.5 | H6: 15828750 | I6: 675000 | J6: Core estrategico
A7: TRITTER | B7: 270000 | C7: 0.2 | D7: 54000 | E7: 180 | F7: 9720000 | G7: 190 | H7: 10260000 | I7: 432000 | J7: Core estrategico
A8: ARTEFATO | B8: 270000 | C8: 0.3 | D8: 81000 | E8: 70 | F8: 5670000 | G8: 73.68 | H8: 5968080 | I8: 324000 | J8: Estrutural B2B
A9: AUBA | B9: 270000 | C9: 0.4 | D9: 108000 | E9: 80 | F9: 8640000 | G9: 84.2 | H9: 9093600 | I9: 1080000 | J9: Core estrategico
A10: BOVETTUS | B10: 206600 | C10: 0.15 | D10: 30990 | E10: 90 | F10: 2789100 | G10: 94.74 | H10: 2935992.6 | I10: 61980 | J10: Entrada/composicao
A11: METTUS | B11: 206600 | C11: 0.2 | D11: 41320 | E11: 95 | F11: 3925400 | G11: 100 | H11: 4132000 | I11: 82640 | J11: Entrada/composicao
A12: TOTAL | D12: 463810 | F12: 47410250 | H12: 50179433 | I12: 2979620 | J12: Referencia de escala
A15: Leitura estrategica | B15: Valor | C15: Diretriz
A16: Cotacao cheia 30d | B16: 47410250 | C16: Manter como potencial de escala do piloto
A17: Cotacao cheia 90d | B17: 50179433 | C17: Usar como alternativa comercial, nao como tese ORIZON
A18: Volume cheio | B18: 463810 | C18: Base para calcular credito operacional de referencia
A19: Credito ORIZON ponderado ref. | B19: 2979620 | C19: Nao liberar integralmente; usar por fases e governanca
A20: Entrada recomendada | B20: Piloto LEGACY | C20: Contrato por etapa com gatilhos de expansao

Sheet Atuacao Grupo Raizen
A1: ORIZON | Modelo de Atuacao no Grupo Raizen
A2: Como entrar, governar, validar e expandir dentro de um grande grupo sucroenergetico
A4: Frente | B4: Interlocutor | C4: Objetivo | D4: Mensagem-chave | E4: Entrega ORIZON | F4: Cadencia
A5: Diretoria | B5: Executivo agricola/suprimentos | C5: Patrocinio do piloto | D5: Raizen como cliente ancora do primeiro ORIZON LEGACY | E5: Business case e governanca | F5: Kickoff + QBR
A6: Agricola corporativo | B6: Gerencia tecnica | C6: Definir janelas e unidades-piloto | D6: Biotecnologia precisa virar padrao operacional mensuravel | E6: Plano tecnico por janela | F6: Mensal
A7: Unidades-piloto | B7: Gerentes agricolas locais | C7: Executar e medir | D7: Menos perda invisivel, mais padronizacao e eficiencia | E7: Diagnosticos TCH e protocolos | F7: Quinzenal
A8: Operacao | B8: Aplicacao/mecanizacao | C8: Corrigir gargalos | D8: O ganho biologico depende de qualidade operacional | E8: Treinamentos e checklists | F8: Mensal
A9: Suprimentos | B9: Compras | C9: Evitar leitura de rebate | D9: ORIZON nao e desconto; e budget tecnico-operacional elegivel | E9: Regras de liberacao por marco | F9: Por etapa
A10: TCH | B10: Parceiro tecnico | C10: Dar independencia tecnica | D10: Quem mede, entende; quem entende, melhora | E10: Laudos, auditorias e treinamentos | F10: Mensal
A11: Mais Maquinas | B11: Parceiro estrutural | C11: Preparar ano 2 | D11: A evolucao operacional vira infraestrutura | E11: Projetos de aplicacao/mecanizacao | F11: Semestral
A12: Comercial NOOA | B12: Rodolfo | C12: Orquestrar conta | D12: Plano de conta enterprise, nao cotacao isolada | E12: CRM, follow-up e proposta | F12: Semanal
A13: Diretoria NOOA | B13: Sponsor interno | C13: Aprovar padrao LEGACY | D13: Raizen define o modelo replicavel do projeto | E13: Decisoes e limites de investimento | F13: Mensal

Sheet Carteira 2026
A1: ORIZON | Carteira 2026
A2: Clientes reais do plano 2026 com potencial, modelo de negocio e regra ORIZON aplicada
A4: Cliente | B4: Area ha | C4: Cana planta | D4: Cana soca | E4: Prioridade | F4: Situacao atual | G4: Acao proposta | H4: Status governanca | I4: Responsavel | J4: Receita potencial | K4: Volume total | L4: Auras | M4: Auba | N4: Nerut | O4: Tritter | P4: Artefato | Q4: Bovettus | R4: Mettus | S4: Bettus | T4: Aufix | U4: Mix estrategico | V4: Score ORIZON reformulado | W4: Nivel ORIZON reformulado | X4: Modelo negocio | Y4: Fator maturidade reformulado | Z4: Teto politica | AA4: Credito ORIZON recomendado
A5: ALCOESTE | B5: 33000 | C5: 4950 | D5: 28050 | E5: Baixa | F5: trabalho concluído sem conversão comercial. Cliente recluso não quis nos receber. Em dificuldades financeiras | G5: Reaproximação gerência, entendimento situação financeira do cliente (proposta de prazo a ser elaborada). Trabalhos em soqueira com Nematicidas | H5: =IF(OR(W5="PRIME",W5="LEGACY"),"Plano executivo obrigatorio",IF(J5>0,"Acompanhar conversao","Prospeccao controlada")) -> Prospeccao controlada | I5: MARCIA | V5: 50 | W5: FOUNDATION | X5: Protocolo e prova de valor | Y5: 0.85
A6: BP BIOENERGY | B6: 200000 | C6: 30000 | D6: 170000 | E6: Média | F6: protocolo Agrocomciência (Auras) CAV finalizado (aguardando relatório), protocolo Bettus concluído porém não caminhou comercialmente por questões técnicas da operação do BT no grupo (mas protocolo foi positivo). SEM PRODUTO VALIDADO PARA COTAÇÃO 25/26 | G6: Aproximação comercial com suprimentos para participação de cotações Bovettus, Mettus e Aufix | H6: =IF(OR(W6="PRIME",W6="LEGACY"),"Plano executivo obrigatorio",IF(J6>0,"Acompanhar conversao","Prospeccao controlada")) -> Prospeccao controlada | I6: MARCIA | V6: 51 | W6: FOUNDATION | X6: Prospeccao controlada | Y6: 0.85
A7: GRUPO ARALCO | B7: 30000 | C7: 4500 | D7: 25500 | E7: Alta | F7: área comercial Auras (plantio). Trabalho com Artefato e boas perspectivas comerciais. Precisamos suplementar com consultorias de apoio para fidelização do cliente | G7: Aproximação, explorando os resultados positivos com Auras e solicitando novas oportunidades comerciais com o Auba e Artefato, baseado em suporte e consultorias externas de apoio | H7: =IF(OR(W7="PRIME",W7="LEGACY"),"Plano executivo obrigatorio",IF(J7>0,"Acompanhar conversao","Prospeccao controlada")) -> Plano executivo obrigatorio | I7: MARCIA | V7: 89 | W7: LEGACY | X7: Expansao estrategica | Y7: 1.25
A8: GRUPO CLEALCO | B8: 40000 | C8: 6000 | D8: 34000 | E8: Alta | F8: campo Auras em soqueira finalizado com resultado pouco expressivo | G8: Estreitar relacionamento técnico e comercial, propor avanço do trabalho semi-comercial com Auras e Nerut. Avanço depende de conexão com a consultoria Planiagro que tem definido os manejos adotados | H8: =IF(OR(W8="PRIME",W8="LEGACY"),"Plano executivo obrigatorio",IF(J8>0,"Acompanhar conversao","Prospeccao controlada")) -> Prospeccao controlada | I8: MARCIA | V8: 60 | W8: FLOW | X8: Protocolo e prova de valor | Y8: 1.05
A9: Grupo CMAA | B9: 120000 | C9: 18000 | D9: 102000 | E9: Alta | F9: Áreas semi comerciais - Cliente adquiriu 500 ha para teste AURAS - 200 ha de AUBA Trabalhar com resultados obtidos a partir de compras passadas | G9: Monitoramento através de Software parceiro GeoData em busca de protocolos personalizados para eficácia de bionematicida e complexo de murcha | H9: =IF(OR(W9="PRIME",W9="LEGACY"),"Plano executivo obrigatorio",IF(J9>0,"Acompanhar conversao","Prospeccao controlada")) -> Plano executivo obrigatorio | I9: RODOLFO | V9: 86 | W9: LEGACY | X9: Protocolo e prova de valor | Y9: 1.25
A10: GRUPO CMNP | B10: 50000 | C10: 7500 | D10: 42500 | E10: Alta | F10: área semi-comercial de Auras em plantio com resultado pouco expressivo | G10: Reaproximação do cliente para tentar participar das cotações de produtos da linha básica como fungos | H10: =IF(OR(W10="PRIME",W10="LEGACY"),"Plano executivo obrigatorio",IF(J10>0,"Acompanhar conversao","Prospeccao controlada")) -> Prospeccao controlada | I10: MARCIA | V10: 47 | W10: FOUNDATION | X10: Prospeccao controlada | Y10: 0.85
A11: GRUPO COCAL | B11: 140000 | C11: 21000 | D11: 119000 | E11: Alta | F11: cliente com aquisição comercial Mettus. Protocolo externo de Auba (breve finalização) | G11: Pendente resultados Protocolo Auba (Fatec) e tentar validar proposta semi-comercial do Auras + Nerut. Continuidade com o Mettus | H11: =IF(OR(W11="PRIME",W11="LEGACY"),"Plano executivo obrigatorio",IF(J11>0,"Acompanhar conversao","Prospeccao controlada")) -> Plano executivo obrigatorio | I11: MARCIA | V11: 97 | W11: LEGACY | X11: Conversao assistida | Y11: 1.25
A12: GRUPO COFCO | B12: 90000 | C12: 13500 | D12: 76500 | E12: Alta | F12: Protocolo com Tritter finalizado sem resultado positivo. Protocolo Auba concluído, produto não validado por questões técnicas da Usina. Protocolo Auras em andamento. Protocolo Bovettus em andamento. | G12: Tentar reverter exclusão do Auba da homologação recém-finalizada. Proposta comercial agressiva com Bovettus e Mettus (reais possibilidades de negócio aturais). Acompanhar de perto campo de Auras com Agrocomciência | H12: =IF(OR(W12="PRIME",W12="LEGACY"),"Plano executivo obrigatorio",IF(J12>0,"Acompanhar conversao","Prospeccao controlada")) -> Plano executivo obrigatorio | I12: MARCIA | V12: 74 | W12: PRIME | X12: Conversao assistida | Y12: 1.15
A13: GRUPO COLOMBO | B13: 60000 | C13: 9000 | D13: 51000 | E13: Média | F13: campos Auras colhidos com resultados não satisfatórios | G13: Estreitar relacionamento técnico e comercial com o cliente e mapear novas possibilidades em 2026. Refazer campos AGD. Copmpras recorrentes durante o ano. | H13: =IF(OR(W13="PRIME",W13="LEGACY"),"Plano executivo obrigatorio",IF(J13>0,"Acompanhar conversao","Prospeccao controlada")) -> Plano executivo obrigatorio | I13: MARCIA | V13: 79 | W13: PRIME | X13: Protocolo e prova de valor | Y13: 1.15
A14: GRUPO CORURIPE | B14: 180000 | C14: 27000 | D14: 153000 | E14: Alta | F14: Campo GD instalado. Área de planejamento pra receber irrigação. 20 ha de padrão NOOA para plantio com possibildiade de vitrine tecnologica | G14: Acompanhamento da área instalada com pacote Auras e Auba em corte de soqueira e estreitamento do relacionamento. Propor: Treinamento de pragas e doenças com Alexandre Sene e Alvaro Sanguino | H14: =IF(OR(W14="PRIME",W14="LEGACY"),"Plano executivo obrigatorio",IF(J14>0,"Acompanhar conversao","Prospeccao controlada")) -> Plano executivo obrigatorio | I14: RODOLFO | V14: 100 | W14: LEGACY | X14: Conversao assistida | Y14: 1.25
A15: GRUPO ITAJOBI | B15: 20000 | C15: 3000 | D15: 17000 | E15: Baixa | F15: campos desenvolvimento Auras e Auba finalizados | G15: Entender melhor como ficará a configuração de time do grupo e resgatar os trabalhos realizados a fim de dar continuidade em âmbito comercial | H15: =IF(OR(W15="PRIME",W15="LEGACY"),"Plano executivo obrigatorio",IF(J15>0,"Acompanhar conversao","Prospeccao controlada")) -> Prospeccao controlada | I15: MARCIA | V15: 66 | W15: FLOW | X15: Entrada por linha basica | Y15: 1.05
A16: GRUPO PEDRA | B16: 95000 | C16: 14250 | D16: 80750 | E16: Alta | F16: áreas comerciais de Bovettus e Auras. Campo Artefato | G16: Ampliar relacionamento nas diversas esferas (técnica e suprimentos) visando participar das cotações. Reaproximar Ipê e fortalecer relacionamento com a Cedro. Proposta de pacote integrado para participar minimamente comercialmente | H16: =IF(OR(W16="PRIME",W16="LEGACY"),"Plano executivo obrigatorio",IF(J16>0,"Acompanhar conversao","Prospeccao controlada")) -> Plano executivo obrigatorio | I16: MARCIA | V16: 97 | W16: LEGACY | X16: Conversao assistida | Y16: 1.25
... A48: USINA UBERABA | B48: 40000 | C48: 6000 | D48: 34000 | E48: Baixa | F48: Áreas semi - comerciais - 200 ha de Auras | G48: Acompanhar áreas semi comerciais e intensificar interação | H48: =IF(OR(W48="PRIME",W48="LEGACY"),"Plano executivo obrigatorio",IF(J48>0,"Acompanhar conversao","Prospeccao controlada")) -> Plano executivo obrigatorio | I48: RODOLFO | V48: 89 | W48: LEGACY | X48: Expansao estrategica | Y48: 1.25

Sheet Especificacao Clientes
A1: ORIZON | Especificacao por Cliente
A2: Leitura operacional por usina/grupo: potencial dinamico, adocao tecnologica e trilha de parceria duradoura
A4: Cliente | B4: Potencial ORIZON reformulado | C4: Estagio de adocao | D4: Nivel ORIZON reformulado | E4: Modelo de negocio | F4: Score ORIZON reformulado | G4: Credito recomendado | H4: Tecnologia de entrada | I4: Diretriz de adocao | J4: Parceiro indicado | K4: Trilha de evolucao | L4: Especificacao executiva | M4: Governanca | N4: Score porte | O4: Score prioridade | P4: Score adocao tecnica | Q4: Score conversao | R4: Score fit ORIZON | S4: Score total | T4: Fila inicial | U4: Proxima decisao
A5: USINA SANTA ADELIA | B5: Alto potencial estruturante | C5: Escala de tecnologia | D5: LEGACY | E5: Expansao estrategica | F5: 93 | G5: 54312.5 | H5: Portfolio core | I5: Expandir Auras/Auba/Tritter como nucleo de eficiencia biologica | J5: TCH + NOOA Tecnica | K5: Consolidar produto validado, ampliar mix core e formalizar plano PRIME/LEGACY | L5: USINA SANTA ADELIA: Alto potencial estruturante com escala de tecnologia. Direcionar ORIZON por adocao tecnologica, nao apenas por potencial historico. | M5: Plano executivo e rotina mensal | N5: 18 | O5: 15 | P5: 25 | Q5: 15 | R5: 20 | S5: 93 | T5: Fila 1 - plano executivo imediato | U5: Designar dono, agenda executiva e plano PRIME/LEGACY
A6: GRUPO COCAL | B6: Alto potencial estruturante | C6: Escala de tecnologia | D6: LEGACY | E6: Conversao assistida | F6: 97 | G6: 72625 | H6: Portfolio core | I6: Expandir Auras/Auba/Tritter como nucleo de eficiencia biologica | J6: TCH + NOOA Tecnica | K6: Consolidar produto validado, ampliar mix core e formalizar plano PRIME/LEGACY | L6: GRUPO COCAL: Alto potencial estruturante com escala de tecnologia. Direcionar ORIZON por adocao tecnologica, nao apenas por potencial historico. | M6: Plano executivo e rotina mensal | N6: 22 | O6: 15 | P6: 25 | Q6: 15 | R6: 20 | S6: 97 | T6: Fila 1 - plano executivo imediato | U6: Designar dono, agenda executiva e plano PRIME/LEGACY
A7: USINA DELTA | B7: Alto potencial estruturante | C7: Escala de tecnologia | D7: LEGACY | E7: Expansao estrategica | F7: 97 | G7: 27625 | H7: Portfolio core | I7: Expandir Auras/Auba/Tritter como nucleo de eficiencia biologica | J7: TCH + NOOA Tecnica | K7: Consolidar produto validado, ampliar mix core e formalizar plano PRIME/LEGACY | L7: USINA DELTA: Potencial de escala com escala de tecnologia. Direcionar ORIZON por adocao tecnologica, nao apenas por potencial historico. | M7: Plano executivo e rotina mensal | N7: 22 | O7: 15 | P7: 25 | Q7: 15 | R7: 20 | S7: 97 | T7: Fila 1 - plano executivo imediato | U7: Designar dono, agenda executiva e plano PRIME/LEGACY
A8: GRUPO ARALCO | B8: Alto potencial estruturante | C8: Escala de tecnologia | D8: LEGACY | E8: Expansao estrategica | F8: 89 | G8: 30250 | H8: Portfolio core | I8: Expandir Auras/Auba/Tritter como nucleo de eficiencia biologica | J8: TCH + NOOA Tecnica | K8: Consolidar produto validado, ampliar mix core e formalizar plano PRIME/LEGACY | L8: GRUPO ARALCO: Potencial de escala com escala de tecnologia. Direcionar ORIZON por adocao tecnologica, nao apenas por potencial historico. | M8: Plano executivo e rotina mensal | N8: 14 | O8: 15 | P8: 25 | Q8: 15 | R8: 20 | S8: 89 | T8: Fila 1 - plano executivo imediato | U8: Designar dono, agenda executiva e plano PRIME/LEGACY
A9: USINA UBERABA | B9: Alto potencial estruturante | C9: Escala de tecnologia | D9: LEGACY | E9: Expansao estrategica | F9: 89 | G9: 34250 | H9: Portfolio core | I9: Expandir Auras/Auba/Tritter como nucleo de eficiencia biologica | J9: TCH + NOOA Tecnica | K9: Consolidar produto validado, ampliar mix core e formalizar plano PRIME/LEGACY | L9: USINA UBERABA: Potencial de escala com escala de tecnologia. Direcionar ORIZON por adocao tecnologica, nao apenas por potencial historico. | M9: Plano executivo e rotina mensal | N9: 14 | O9: 15 | P9: 25 | Q9: 15 | R9: 20 | S9: 89 | T9: Fila 1 - plano executivo imediato | U9: Designar dono, agenda executiva e plano PRIME/LEGACY
A10: GRUPO VITERRA | B10: Alto potencial estruturante | C10: Escala de tecnologia | D10: LEGACY | E10: Expansao estrategica | F10: 93 | G10: 28750 | H10: Portfolio core | I10: Expandir Auras/Auba/Tritter como nucleo de eficiencia biologica | J10: TCH + NOOA Tecnica | K10: Consolidar produto validado, ampliar mix core e formalizar plano PRIME/LEGACY | L10: GRUPO VITERRA: Potencial de escala com escala de tecnologia. Direcionar ORIZON por adocao tecnologica, nao apenas por potencial historico. | M10: Plano executivo e rotina mensal | N10: 18 | O10: 15 | P10: 25 | Q10: 15 | R10: 20 | S10: 93 | T10: Fila 1 - plano executivo imediato | U10: Designar dono, agenda executiva e plano PRIME/LEGACY
A11: GRUPO RAÍZEN | B11: Alto potencial estruturante | C11: Piloto enterprise LEGACY | D11: LEGACY | E11: Piloto LEGACY Raizen | F11: 95 | G11: 23625 | H11: Portfolio core | I11: Governanca enterprise, validacao TCH e expansao plurianual | J11: TCH ano 1 + Mais Maquinas ano 2 | K11: Entrar por unidades-piloto, validar com TCH, padronizar e renovar em contrato plurianual | L11: GRUPO RAÍZEN: Ancora estrategica com piloto enterprise legacy. Direcionar ORIZON por adocao tecnologica, nao apenas por potencial historico. | M11: Plano executivo e rotina mensal | N11: 25 | O11: 15 | P11: 23 | Q11: 12 | R11: 20 | S11: 95 | T11: Fila 1 - plano executivo imediato | U11: Abrir comite LEGACY e validar piloto governado
A12: GRUPO CORURIPE | B12: Alto potencial estruturante | C12: Escala de tecnologia | D12: LEGACY | E12: Conversao assistida | F12: 100 | G12: 24500 | H12: Portfolio core | I12: Expandir Auras/Auba/Tritter como nucleo de eficiencia biologica | J12: TCH + NOOA Tecnica | K12: Consolidar produto validado, ampliar mix core e formalizar plano PRIME/LEGACY | L12: GRUPO CORURIPE: Alto potencial estruturante com escala de tecnologia. Direcionar ORIZON por adocao tecnologica, nao apenas por potencial historico. | M12: Plano executivo e rotina mensal | N12: 25 | O12: 15 | P12: 25 | Q12: 15 | R12: 20 | S12: 100 | T12: Fila 1 - plano executivo imediato | U12: Designar dono, agenda executiva e plano PRIME/LEGACY
A13: USINA BRANCO PERES | B13: Alto potencial estruturante | C13: Escala de tecnologia | D13: LEGACY | E13: Conversao assistida | F13: 89 | G13: 31812.5 | H13: Portfolio core | I13: Expandir Auras/Auba/Tritter como nucleo de eficiencia biologica | J13: TCH + NOOA Tecnica | K13: Consolidar produto validado, ampliar mix core e formalizar plano PRIME/LEGACY | L13: USINA BRANCO PERES: Potencial de escala com escala de tecnologia. Direcionar ORIZON por adocao tecnologica, nao apenas por potencial historico. | M13: Plano executivo e rotina mensal | N13: 14 | O13: 15 | P13: 25 | Q13: 15 | R13: 20 | S13: 89 | T13: Fila 1 - plano executivo imediato | U13: Designar dono, agenda executiva e plano PRIME/LEGACY
A14: GRUPO PEDRA | B14: Alto potencial estruturante | C14: Escala de tecnologia | D14: LEGACY | E14: Conversao assistida | F14: 97 | G14: 30562.5 | H14: Portfolio core | I14: Expandir Auras/Auba/Tritter como nucleo de eficiencia biologica | J14: TCH + NOOA Tecnica | K14: Consolidar produto validado, ampliar mix core e formalizar plano PRIME/LEGACY | L14: GRUPO PEDRA: Alto potencial estruturante com escala de tecnologia. Direcionar ORIZON por adocao tecnologica, nao apenas por potencial historico. | M14: Plano executivo e rotina mensal | N14: 22 | O14: 15 | P14: 25 | Q14: 15 | R14: 20 | S14: 97 | T14: Fila 1 - plano executivo imediato | U14: Designar dono, agenda executiva e plano PRIME/LEGACY
A15: USINA CERRADÃO | B15: Potencial de escala | C15: Escala de tecnologia | D15: PRIME | E15: Protocolo e prova de valor | F15: 76 | G15: 23100 | H15: Portfolio core | I15: Expandir Auras/Auba/Tritter como nucleo de eficiencia biologica | J15: NOOA Tecnica + consultoria externa | K15: Consolidar produto validado, ampliar mix core e formalizar plano PRIME/LEGACY | L15: USINA CERRADÃO: Potencial de escala com escala de tecnologia. Direcionar ORIZON por adocao tecnologica, nao apenas por potencial historico. | M15: Acompanhamento comercial por marco | N15: 18 | O15: 5 | P15: 25 | Q15: 10 | R15: 18 | S15: 76 | T15: Fila 2 - conversao assistida 30 dias | U15: Converter oportunidade em proposta com mix core e marco tecnico
A16: USINA CALIFÓRNIA | B16: Alto potencial estruturante | C16: Escala de tecnologia | D16: LEGACY | E16: Conversao assistida | F16: 85 | G16: 16187.5 | H16: Portfolio core | I16: Expandir Auras/Auba/Tritter como nucleo de eficiencia biologica | J16: TCH + NOOA Tecnica | K16: Consolidar produto validado, ampliar mix core e formalizar plano PRIME/LEGACY | L16: USINA CALIFÓRNIA: Potencial de escala com escala de tecnologia. Direcionar ORIZON por adocao tecnologica, nao apenas por potencial historico. | M16: Plano executivo e rotina mensal | N16: 10 | O16: 15 | P16: 25 | Q16: 15 | R16: 20 | S16: 85 | T16: Fila 1 - plano executivo imediato | U16: Designar dono, agenda executiva e plano PRIME/LEGACY
... A49: ACESSÍVEL | B49: Entrada ou reaproximacao controlada | C49: Diagnostico e qualificacao | D49: FOUNDATION | E49: Prospeccao controlada | F49: 28 | G49: 0 | H49: Diagnostico | I49: Comecar por diagnostico, dor operacional e protocolo mensuravel | J49: Comercial + NOOA Tecnica | K49: Qualificar decisor, dor operacional e janela agricola antes de liberar investimento | L49: ACESSÍVEL: Potencial a qualificar com diagnostico e qualificacao. Direcionar ORIZON por adocao tecnologica, nao apenas por potencial historico. | M49: Acompanhamento comercial por marco | N49: 10 | O49: 0 | P49: 5 | Q49: 5 | R49: 8 | S49: 28 | T49: Fila 4 - qualificacao sem investimento | U49: Reaproximar, qualificar dor operacional e acesso a decisor

Sheet Politica ORIZON
A1: ORIZON | Politica de Credito por Cotacao Vigente
A2: O teto do cliente nasce da cotacao vigente do mes; o credito liberavel nasce da compra efetiva por produto. Cotacao limita, compra gera.
A4: Parametro | B4: Valor | C4: Como usar | D4: Observacao | E4: Coluna1 | F4: Coluna2
A5: Mes vigente | B5: Mês atual | C5: Referencia comercial da cotacao ativa | D5: Atualizar a cada ciclo mensal.
A6: Cotacao vigente do cliente | B6: 100000 | C6: Base para teto mensal ORIZON | D6: Substituir pelo valor total cotado no mes.
A7: Credito gerado pela compra | B7: =SUM(D24:D32) -> #NAME? | C7: Soma do simulador por produto | D7: Calculado por quantidade comprada x credito por L/Kg.
A8: Nivel do cliente | B8: PRIME | C8: Define percentual de teto | D8: Usar nivel reformulado da aba Especificacao Clientes.
A9: Teto ORIZON do mes | B9: =_xludf.XLOOKUP(B8,A14:A17,E14:E17,0) -> #NAME? | C9: Cotacao vigente x percentual do nivel | D9: Limite maximo antes da compra.
A10: Credito liberavel no mes | B10: =MIN(B7,B9) -> #NAME? | C10: Menor entre credito gerado e teto do mes | D10: Nao liberar credito sem compra correspondente.
A13: Nivel | B13: Score reformulado | C13: % teto sobre cotacao vigente | D13: Exigencia de compra | E13: Teto calculado do mes | F13: Credito liberavel | G13: Gatilho de uso | H13: Governanca | I13: Regra de protecao
A14: FOUNDATION | B14: 0 a 54 | C14: 0.02 | D14: Compra confirmada ou pedido firme | E14: =$B$6*C14 -> 2000 | F14: =MIN($B$7,E14) -> #NAME? | G14: Diagnostico, treinamento ou prova tecnica pequena | H14: Acompanhamento comercial por marco | I14: Sem antecipacao; liberar apos compra ou pedido firme.
A15: FLOW | B15: 55 a 69 | C15: 0.03 | D15: Compra confirmada + plano tecnico simples | E15: =$B$6*C15 -> 3000 | F15: =MIN($B$7,E15) -> #NAME? | G15: Prova de valor e consolidacao de recorrencia | H15: Dono comercial e follow-up mensal | I15: Credito limitado ao mix comprado no mes.
A16: PRIME | B16: 70 a 84 | C16: 0.045 | D16: Compra confirmada + mix core ou trilha de conversao | E16: =$B$6*C16 -> 4500 | F16: =MIN($B$7,E16) -> #NAME? | G16: Consultoria, TCH, laudo, treinamento e apoio tecnico | H16: Plano executivo e rotina mensal | I16: Credito condicionado a marco tecnico e margem preservada.
A17: LEGACY | B17: 85 a 100 ou ancora | C17: 0.06 | D17: Compra confirmada + governanca executiva | E17: =$B$6*C17 -> 6000 | F17: =MIN($B$7,E17) -> #NAME? | G17: Success Cycle, TCH, Mais Maquinas e expansao plurianual | H17: Comite mensal e plano por unidade/grupo | I17: Nao usar como rebate; liberar por fase e evidencia.
A20: Regra operacional
A21: Credito ORIZON nao e desconto automatico: ele e um budget tecnico-operacional gerado pela compra, limitado pela cotacao vigente do mes e liberado por marco de execucao.
A23: Produto | B23: Quantidade comprada (L ou Kg) | C23: Credito por L ou Kg | D23: Credito gerado | E23: Receita da compra
A24: Auras | B24: 0 | C24: =_xludf.XLOOKUP(A24,'Produtos e Pesos'!$A$5:$A$13,'Produtos e Pesos'!$G$5:$G$13,0) -> #NAME? | D24: =B24*C24 -> #NAME? | E24: =B24*_xludf.XLOOKUP(A24,'Produtos e Pesos'!$A$5:$A$13,'Produtos e Pesos'!$D$5:$D$13,0) -> #NAME?
A25: Auba | B25: 0 | C25: =_xludf.XLOOKUP(A25,'Produtos e Pesos'!$A$5:$A$13,'Produtos e Pesos'!$G$5:$G$13,0) -> #NAME? | D25: =B25*C25 -> #NAME? | E25: =B25*_xludf.XLOOKUP(A25,'Produtos e Pesos'!$A$5:$A$13,'Produtos e Pesos'!$D$5:$D$13,0) -> #NAME?
A26: Nerut | B26: 0 | C26: =_xludf.XLOOKUP(A26,'Produtos e Pesos'!$A$5:$A$13,'Produtos e Pesos'!$G$5:$G$13,0) -> #NAME? | D26: =B26*C26 -> #NAME? | E26: =B26*_xludf.XLOOKUP(A26,'Produtos e Pesos'!$A$5:$A$13,'Produtos e Pesos'!$D$5:$D$13,0) -> #NAME?
A27: Tritter | B27: 0 | C27: =_xludf.XLOOKUP(A27,'Produtos e Pesos'!$A$5:$A$13,'Produtos e Pesos'!$G$5:$G$13,0) -> #NAME? | D27: =B27*C27 -> #NAME? | E27: =B27*_xludf.XLOOKUP(A27,'Produtos e Pesos'!$A$5:$A$13,'Produtos e Pesos'!$D$5:$D$13,0) -> #NAME?
A28: Artefato | B28: 0 | C28: =_xludf.XLOOKUP(A28,'Produtos e Pesos'!$A$5:$A$13,'Produtos e Pesos'!$G$5:$G$13,0) -> #NAME? | D28: =B28*C28 -> #NAME? | E28: =B28*_xludf.XLOOKUP(A28,'Produtos e Pesos'!$A$5:$A$13,'Produtos e Pesos'!$D$5:$D$13,0) -> #NAME?
A29: Bovettus | B29: 0 | C29: =_xludf.XLOOKUP(A29,'Produtos e Pesos'!$A$5:$A$13,'Produtos e Pesos'!$G$5:$G$13,0) -> #NAME? | D29: =B29*C29 -> #NAME? | E29: =B29*_xludf.XLOOKUP(A29,'Produtos e Pesos'!$A$5:$A$13,'Produtos e Pesos'!$D$5:$D$13,0) -> #NAME?
A30: Mettus | B30: 0 | C30: =_xludf.XLOOKUP(A30,'Produtos e Pesos'!$A$5:$A$13,'Produtos e Pesos'!$G$5:$G$13,0) -> #NAME? | D30: =B30*C30 -> #NAME? | E30: =B30*_xludf.XLOOKUP(A30,'Produtos e Pesos'!$A$5:$A$13,'Produtos e Pesos'!$D$5:$D$13,0) -> #NAME?
A31: Bettus | B31: 0 | C31: =_xludf.XLOOKUP(A31,'Produtos e Pesos'!$A$5:$A$13,'Produtos e Pesos'!$G$5:$G$13,0) -> #NAME? | D31: =B31*C31 -> #NAME? | E31: =B31*_xludf.XLOOKUP(A31,'Produtos e Pesos'!$A$5:$A$13,'Produtos e Pesos'!$D$5:$D$13,0) -> #NAME?
A32: Aufix | B32: 0 | C32: =_xludf.XLOOKUP(A32,'Produtos e Pesos'!$A$5:$A$13,'Produtos e Pesos'!$G$5:$G$13,0) -> #NAME? | D32: =B32*C32 -> #NAME? | E32: =B32*_xludf.XLOOKUP(A32,'Produtos e Pesos'!$A$5:$A$13,'Produtos e Pesos'!$D$5:$D$13,0) -> #NAME?
A34: Exemplo de decisao | B34: Formula conceitual | C34: Leitura
A35: Credito gerado | B35: Soma(D24:D32) | C35: Soma das compras por produto.
A36: Teto do cliente | B36: Cotacao vigente x percentual do nivel | C36: Limite economico do mes.
A37: Credito liberavel | B37: Menor entre credito gerado e teto | C37: Nao pode superar compra nem teto.

Sheet Produtos e Pesos
A1: ORIZON | Produtos, Pesos e Credito por Compra
A2: Credito gerado por unidade comprada: valor vigente por L/Kg x fator de credito do papel no mix; dose/ha estima credito por hectare.
A4: Produto | B4: Papel | C4: Fator credito | D4: Valor vigente (L ou Kg) | E4: Dose/ha (L ou Kg) | F4: Receita/ha estimada | G4: Credito por L ou Kg | H4: Credito por ha | I4: Regra de uso
A5: Auras | B5: Core estrategico | C5: 0.05 | D5: 221 | E5: 0.25 | F5: =D5*E5 -> 55.25 | G5: =D5*C5 -> 11.05 | H5: =G5*E5 -> 2.7625 | I5: Gera credito pleno; usar para carteira PRIME/LEGACY e expansao de portfolio.
A6: Auba | B6: Core estrategico | C6: 0.08 | D6: 80 | E6: 0.4 | F6: =D6*E6 -> 32 | G6: =D6*C6 -> 6.4 | H6: =G6*E6 -> 2.56 | I6: Gera credito pleno; base de recorrencia biologica e integracao operacional.
A7: Nerut | B7: Estrutural B2B | C7: 0.02 | D7: 180 | E7: 0.4 | F7: =D7*E7 -> 72 | G7: =D7*C7 -> 3.6 | H7: =G7*E7 -> 1.44 | I7: Credito intermediario; acelera prova tecnica e abre conversao.
A8: Tritter | B8: Core estrategico | C8: 0.06 | D8: 180 | E8: 0.2 | F8: =D8*E8 -> 36 | G8: =D8*C8 -> 10.8 | H8: =G8*E8 -> 2.16 | I8: Gera credito pleno quando compoe pacote de sanidade e protecao biologica.
A9: Artefato | B9: Estrutural B2B | C9: 0.02 | D9: 70 | E9: 0.3 | F9: =D9*E9 -> 21 | G9: =D9*C9 -> 1.4 | H9: =G9*E9 -> 0.42 | I9: Credito de estrutura B2B; sustenta operacao sem virar desconto direto.
A10: Bovettus | B10: Entrada/composicao | C10: 0.02 | D10: 90 | E10: 0.15 | F10: =D10*E10 -> 13.5 | G10: =D10*C10 -> 1.8 | H10: =G10*E10 -> 0.27 | I10: Faixa proxima ao B2B; abre porta para mix core sem desvalorizar entrada.
A11: Mettus | B11: Entrada/composicao | C11: 0.02 | D11: 95 | E11: 0.2 | F11: =D11*E11 -> 19 | G11: =D11*C11 -> 1.9 | H11: =G11*E11 -> 0.38 | I11: Faixa proxima ao B2B; recorrencia e composicao de carteira.
A12: Bettus | B12: Entrada/composicao | C12: 0.02 | D12: 30 | E12: 1 | F12: =D12*E12 -> 30 | G12: =D12*C12 -> 0.6 | H12: =G12*E12 -> 0.6 | I12: Faixa proxima ao B2B; composicao operacional com baixo valor unitario.
A13: Aufix | B13: Estrutural B2B | C13: 0.02 | D13: 22 | E13: 0.3 | F13: =D13*E13 -> 6.6 | G13: =D13*C13 -> 0.44 | H13: =G13*E13 -> 0.132 | I13: Credito de estrutura B2B; apoio operacional e integracao de aplicacao.
A15: Leitura da calibragem
A16: Core estrategico | B16: 20% do valor por L/Kg | C16: Maior geracao porque sustenta tese tecnologica e recorrencia premium.
A17: Acelerador tecnico | B17: 16% do valor por L/Kg | C17: Fica abaixo do core, mas acima de mero produto de entrada quando abre conversao.
A18: Estrutural B2B | B18: 14% do valor por L/Kg | C18: Faixa de apoio operacional B2B, preservando margem e governanca.
A19: Entrada/composicao | B19: 13% do valor por L/Kg | C19: Fica parecido com B2B para nao punir a entrada, mas sem superar o estrutural.
A20: Formula | B20: Credito por L ou Kg = Valor vigente x Fator credito; Credito por ha = Credito por L ou Kg x Dose/ha.

Sheet Pipeline Mensal
A1: ORIZON | Pipeline Mensal
A2: Distribuicao mensal do potencial extraida da aba Resumo matriz
A4: Mes | B4: Potencial R$ | C4: Participacao
A5: JANEIRO | B5: 557262.5 | C5: =B5/SUM($B$5:$B$16) -> 0.041406912
A6: FEVEREIRO | B6: 1114525 | C6: =B6/SUM($B$5:$B$16) -> 0.082813824
A7: MARÇO | B7: 1114525 | C7: =B7/SUM($B$5:$B$16) -> 0.082813824
A8: ABRIL | B8: 1114525 | C8: =B8/SUM($B$5:$B$16) -> 0.082813824
A9: MAIO | B9: 557262.5 | C9: =B9/SUM($B$5:$B$16) -> 0.041406912
A10: JUNHO | B10: 0 | C10: =B10/SUM($B$5:$B$16) -> 0
A11: JULHO | B11: 0 | C11: =B11/SUM($B$5:$B$16) -> 0
A12: AGOSTO | B12: 2250025 | C12: =B12/SUM($B$5:$B$16) -> 0.16718618
A13: SETEMBRO | B13: 2250025 | C13: =B13/SUM($B$5:$B$16) -> 0.16718618
A14: OUTUBRO | B14: 2250025 | C14: =B14/SUM($B$5:$B$16) -> 0.16718618
A15: NOVEMBRO | B15: 2250025 | C15: =B15/SUM($B$5:$B$16) -> 0.16718618
A16: DEZEMBRO | B16: 0 | C16: =B16/SUM($B$5:$B$16) -> 0

Sheet Parceiros Operacionais
A1: ORIZON | Parceiros Operacionais
A2: Uso recomendado dos parceiros conforme modelo de negocio e potencial do cliente
A4: Parceiro | B4: Papel | C4: Quando acionar | D4: Entrega esperada | E4: Nivel recomendado
A5: TCH Gestao Agricola | B5: Braco tecnico | C5: PRIME/LEGACY, validacao tecnica, auditoria, treinamento | D5: Diagnostico, laudo, plano de correcao, evidencia de campo | E5: PRIME+
A6: Mais Maquinas | B6: Braco estrutural | C6: Quando a barreira for mecanizacao, aplicacao ou padrao operacional | D6: Plano estrutural, recomendacao de aplicacao e melhoria operacional | E6: PRIME+
A7: NOOA Tecnica | B7: Biotecnologia | C7: Todos os niveis com potencial positivo | D7: Protocolo biologico e leitura agronomica | E7: Todos
A8: Comercial | B8: Orquestracao | C8: Toda conta com potencial ou prioridade definida | D8: Plano de conta, proposta e follow-up | E8: Todos
A9: Consultoria externa | B9: Prova de valor | C9: Clientes reclusos, resultados inconclusivos ou conversao complexa | D9: Relatorio independente e ponte com decisores | E9: FLOW+
A10: Suprimentos cliente | B10: Conversao | C10: Contas com produto validado e oportunidade de cotacao | D10: Acesso a cotacao e condicao saudavel | E10: PRIME+

Sheet Acoes por Modelo
A1: ORIZON | Acoes por Modelo
A2: Playbook de consistencia para tratar modelos de negocio individuais
A4: Modelo de negocio | B4: Objetivo | C4: Politica saudavel | D4: Proxima acao | E4: Indicador
A5: Piloto LEGACY Raizen | B5: Criar primeiro caso enterprise ORIZON | C5: Nao vender desconto; estruturar piloto com governanca, diagnostico TCH e trilha plurianual | D5: Comite executivo + plano 2026/2027 | E5: Contrato, areas validadas e expansao
A6: Expansao estrategica | B6: Capturar potencial com portfolio integrado | C6: Investimento tecnico condicionado a plano executivo e mix core | D6: Reuniao decisoria + proposta ORIZON PRIME/LEGACY | E6: Receita e hectares evoluidos
A7: Conversao assistida | B7: Converter oportunidade relevante em recorrencia | C7: Apoio tecnico limitado por teto e evidencia de campo | D7: Plano tecnico-comercial com responsavel e prazo | E7: Conversao e margem
A8: Entrada por linha basica | B8: Abrir relacionamento sem diluir posicionamento premium | C8: Nao financiar desconto; usar linha basica como porta de entrada para AURAS/AUBA | D8: Protocolo com trilha de upsell | E8: Mix estrategico
A9: Protocolo e prova de valor | B9: Reduzir risco percebido | C9: Protocolo pequeno, mensuravel e com criterio de continuidade | D9: Diagnostico + relatorio evolutivo | E9: Laudo e nova area
A10: Prospeccao controlada | B10: Preservar foco comercial | C10: Sem investimento relevante antes de acesso, decisor e dor operacional clara | D10: Reaproximacao e qualificacao | E10: Avanco de etapa

Sheet Modelo Pontuacao
A1: ORIZON | Modelo de Pontuacao Reformulado
A2: Regua de partida para iniciar a operacao do zero em todos os clientes, sem depender do status de governanca inicial.
A4: Componente | B4: Peso max. | C4: Fonte principal | D4: Regra executiva
A5: Porte operacional | B5: 25 | C5: Area ha | D5: Mede tamanho da oportunidade agricola; areas maiores sobem na fila mesmo com CRM zerado.
A6: Prioridade comercial | B6: 15 | C6: Prioridade | D6: Alta, Media e Baixa preservam o julgamento comercial da carteira.
A7: Adocao tecnica | B7: 25 | C7: Estagio + historico | D7: Valoriza escala/prova de tecnologia e penaliza ausencia de validacao ou rejeicao tecnica.
A8: Conversao operacional | B8: 15 | C8: Modelo + acao proposta | D8: Mede proximidade de acesso, cotacao, decisor e clareza do proximo movimento.
A9: Fit ORIZON | B9: 20 | C9: Tecnologia, parceiro e governanca | D9: Valoriza portfolio core, TCH, Mais Maquinas e trilhas PRIME/LEGACY.
A10: Total | B10: 100 | C10: Soma dos componentes | D10: Score final usado para fila inicial e nivel ORIZON reformulado.
A12: Faixa de score | B12: Nivel | C12: Fila inicial | D12: Conduta
A13: 85 a 100 | B13: LEGACY | C13: Fila 1 | D13: Plano executivo imediato, dono comercial e governanca mensal.
A14: 70 a 84 | B14: PRIME | C14: Fila 2 | D14: Conversao assistida em 30 dias com mix core e marco tecnico.
A15: 55 a 69 | B15: FLOW | C15: Fila 3 | D15: Prova de valor em 60 dias com criterio de continuidade.
A16: 0 a 54 | B16: FOUNDATION | C16: Fila 4 | D16: Qualificacao sem investimento relevante antes de dor, acesso e decisor.
A18: Resumo reformulado
A19: Clientes mapeados | B19: 45 | D19: Score medio | E19: 66.711111
A20: LEGACY | B20: 14 | D20: PRIME | E20: 9 | G20: FLOW | H20: 5
A21: FOUNDATION | B21: 17 | D21: Fila 1 | E21: 14 | G21: Fila 2 | H21: 9
D22: Fila 3 | E22: 5 | G22: Fila 4 | H22: 17
A24: Top clientes por score | B24: Score | C24: Nivel | D24: Fila | E24: Area ha | F24: Prioridade | G24: Modelo | H24: Proxima decisao
A25: GRUPO CORURIPE | B25: 100 | C25: LEGACY | D25: Fila 1 - plano executivo imediato | E25: 180000 | F25: Alta | G25: Conversao assistida | H25: Designar dono, agenda executiva e plano PRIME/LEGACY
A26: GRUPO TEREOS | B26: 100 | C26: LEGACY | D26: Fila 1 - plano executivo imediato | E26: 190000 | F26: Alta | G26: Conversao assistida | H26: Designar dono, agenda executiva e plano PRIME/LEGACY
A27: GRUPO COCAL | B27: 97 | C27: LEGACY | D27: Fila 1 - plano executivo imediato | E27: 140000 | F27: Alta | G27: Conversao assistida | H27: Designar dono, agenda executiva e plano PRIME/LEGACY
A28: USINA DELTA | B28: 97 | C28: LEGACY | D28: Fila 1 - plano executivo imediato | E28: 120000 | F28: Alta | G28: Expansao estrategica | H28: Designar dono, agenda executiva e plano PRIME/LEGACY
A29: GRUPO PEDRA | B29: 97 | C29: LEGACY | D29: Fila 1 - plano executivo imediato | E29: 95000 | F29: Alta | G29: Conversao assistida | H29: Designar dono, agenda executiva e plano PRIME/LEGACY
A30: GRUPO RAÍZEN | B30: 95 | C30: LEGACY | D30: Fila 1 - plano executivo imediato | E30: 1000000 | F30: Alta | G30: Piloto LEGACY Raizen | H30: Abrir comite LEGACY e validar piloto governado
A31: USINA SANTA ADELIA | B31: 93 | C31: LEGACY | D31: Fila 1 - plano executivo imediato | E31: 50000 | F31: Alta | G31: Expansao estrategica | H31: Designar dono, agenda executiva e plano PRIME/LEGACY
A32: GRUPO VITERRA | B32: 93 | C32: LEGACY | D32: Fila 1 - plano executivo imediato | E32: 50000 | F32: Alta | G32: Expansao estrategica | H32: Designar dono, agenda executiva e plano PRIME/LEGACY
A33: GRUPO ARALCO | B33: 89 | C33: LEGACY | D33: Fila 1 - plano executivo imediato | E33: 30000 | F33: Alta | G33: Expansao estrategica | H33: Designar dono, agenda executiva e plano PRIME/LEGACY
A34: USINA UBERABA | B34: 89 | C34: LEGACY | D34: Fila 1 - plano executivo imediato | E34: 40000 | F34: Alta | G34: Expansao estrategica | H34: Designar dono, agenda executiva e plano PRIME/LEGACY
